{"name":"LinkSwimDown","loopStartFrame":"0","frames":[{"childFrames":[{"zIndex":"0","xDir":"1","yDir":"1","tags":"a","rect":{"topLeftPoint":{"x":"16","y":"0","className":"Point"},"botRightPoint":{"x":"32","y":"16","className":"Point"},"className":"Rect"},"duration":"0.26666666666666666","offset":{"x":"0","y":"-7","className":"Point"},"parentFrameIndex":"1","className":"Frame"}],"zIndex":"0","xDir":"1","yDir":"1","tags":"j","rect":{"topLeftPoint":{"x":"32","y":"144","className":"Point"},"botRightPoint":{"x":"48","y":"160","className":"Point"},"className":"Rect"},"duration":"0.26666666666666666","offset":{"x":"0","y":"7","className":"Point"},"className":"Frame"},{"childFrames":[{"zIndex":"0","xDir":"1","yDir":"1","tags":"a","rect":{"topLeftPoint":{"x":"16","y":"0","className":"Point"},"botRightPoint":{"x":"32","y":"16","className":"Point"},"className":"Rect"},"duration":"0.26666666666666666","offset":{"x":"0","y":"-6","className":"Point"},"parentFrameIndex":"1","className":"Frame"}],"zIndex":"0","xDir":"-1","yDir":"1","tags":"j","rect":{"topLeftPoint":{"x":"32","y":"144","className":"Point"},"botRightPoint":{"x":"48","y":"160","className":"Point"},"className":"Rect"},"duration":"0.26666666666666666","offset":{"x":"0","y":"7","className":"Point"},"className":"Frame"}],"alignment":"topleft","wrapMode":"loop","spriteJson":"","spritesheetPath":"assets/spritesheets/link2.png","className":"Sprite"}