{"name":"PotBreak","loopStartFrame":"0","frames":[{"drawBelowParent":"false","rect":{"topLeftPoint":{"x":"20","y":"200","className":"Point"},"botRightPoint":{"x":"35","y":"216","className":"Point"},"className":"Rect"},"duration":"0.066","offset":{"x":"0","y":"0","className":"Point"},"className":"Frame"},{"drawBelowParent":"false","rect":{"topLeftPoint":{"x":"48","y":"199","className":"Point"},"botRightPoint":{"x":"67","y":"218","className":"Point"},"className":"Rect"},"duration":"0.066","offset":{"x":"0","y":"0","className":"Point"},"className":"Frame"},{"drawBelowParent":"false","rect":{"topLeftPoint":{"x":"77","y":"197","className":"Point"},"botRightPoint":{"x":"99","y":"219","className":"Point"},"className":"Rect"},"duration":"0.066","offset":{"x":"0","y":"0","className":"Point"},"className":"Frame"},{"drawBelowParent":"false","rect":{"topLeftPoint":{"x":"106","y":"196","className":"Point"},"botRightPoint":{"x":"132","y":"220","className":"Point"},"className":"Rect"},"duration":"0.066","offset":{"x":"0","y":"0","className":"Point"},"className":"Frame"},{"drawBelowParent":"false","rect":{"topLeftPoint":{"x":"137","y":"196","className":"Point"},"botRightPoint":{"x":"164","y":"221","className":"Point"},"className":"Rect"},"duration":"0.066","offset":{"x":"0","y":"0","className":"Point"},"className":"Frame"},{"drawBelowParent":"false","rect":{"topLeftPoint":{"x":"166","y":"196","className":"Point"},"botRightPoint":{"x":"195","y":"224","className":"Point"},"className":"Rect"},"duration":"0.066","offset":{"x":"0","y":"0","className":"Point"},"className":"Frame"},{"drawBelowParent":"false","rect":{"topLeftPoint":{"x":"202","y":"196","className":"Point"},"botRightPoint":{"x":"227","y":"221","className":"Point"},"className":"Rect"},"duration":"0.066","offset":{"x":"0","y":"0","className":"Point"},"className":"Frame"},{"drawBelowParent":"false","rect":{"topLeftPoint":{"x":"234","y":"200","className":"Point"},"botRightPoint":{"x":"252","y":"223","className":"Point"},"className":"Rect"},"duration":"0.066","offset":{"x":"0","y":"0","className":"Point"},"className":"Frame"}],"alignment":"center","wrapMode":"once","spriteJson":"","spritesheetPath":"assets/spritesheets/objects.png","className":"Sprite","path":"assets/sprites/PotBreak.json"}